.gitignore
LICENSE
README.rst
setup.cfg
setup.py
tox.ini
requirements/install.txt
requirements/test.txt
tests/test_config.py
tests/test_main.py
tests/test_routes.py
tests/apps/development.ini
tests/apps/setup.py
tests/apps/tomb_cli_testapps/__init__.py
tests/apps/tomb_cli_testapps/standard_views.py
tests/fixtures/app.yaml
tests/fixtures/bad_env_var_directive.yaml
tests/fixtures/bad_include.yaml
tests/fixtures/complete_app.yaml
tests/fixtures/env_vars.yaml
tests/fixtures/logging.yaml
tests/fixtures/server.yaml
tomb_cli/__about__.py
tomb_cli/__init__.py
tomb_cli/config.py
tomb_cli/main.py
tomb_cli/routes.py
tomb_cli/serve.py
tomb_cli.egg-info/PKG-INFO
tomb_cli.egg-info/SOURCES.txt
tomb_cli.egg-info/dependency_links.txt
tomb_cli.egg-info/entry_points.txt
tomb_cli.egg-info/requires.txt
tomb_cli.egg-info/top_level.txt
tomb_cli.egg-info/zip-safe