Metadata-Version: 1.1
Name: tomb-cli
Version: 0.0.4
Summary: Top level CLI command for tomb
Home-page: http://github.com/tomborine/tomb_cli
Author: John Anderson
Author-email: sontek@gmail.com
License: MIT
Platform: UNKNOWN
Classifier: Development Status :: 5 - Production/Stable
Classifier: Intended Audience :: Developers
Classifier: License :: OSI Approved :: MIT License
Classifier: Programming Language :: Python :: 3
Classifier: Programming Language :: Python :: 3.4
